{
  "name": "leduc_nfsp_vs_cfr_s0",
  "game": "leduc_poker",
  "agent": "nfsp_selfplay",
  "expert": "cfr",
  "seed": 0,
  "cfr_iters": 400,
  "cfr_exploitability": 0.0264,
  "episodes": 600000,
  "final_return_vs_expert": -0.7017,
  "curve": [
    {
      "episode": 40000,
      "return_vs_expert": -0.7535
    },
    {
      "episode": 80000,
      "return_vs_expert": -0.8193
    },
    {
      "episode": 120000,
      "return_vs_expert": -0.7262
    },
    {
      "episode": 160000,
      "return_vs_expert": -0.7105
    },
    {
      "episode": 200000,
      "return_vs_expert": -0.772
    },
    {
      "episode": 240000,
      "return_vs_expert": -0.8445
    },
    {
      "episode": 280000,
      "return_vs_expert": -0.6865
    },
    {
      "episode": 320000,
      "return_vs_expert": -0.7195
    },
    {
      "episode": 360000,
      "return_vs_expert": -0.8375
    },
    {
      "episode": 400000,
      "return_vs_expert": -0.7075
    },
    {
      "episode": 440000,
      "return_vs_expert": -0.734
    },
    {
      "episode": 480000,
      "return_vs_expert": -0.7392
    },
    {
      "episode": 520000,
      "return_vs_expert": -0.7072
    },
    {
      "episode": 560000,
      "return_vs_expert": -0.7167
    },
    {
      "episode": 600000,
      "return_vs_expert": -0.7017
    }
  ]
}